{"schema":"ora.smt.report.v1","source_file":"ora-example/tuples/tuple_basics.ora","generated_at_unix":1771006779,"settings":{"verify_mode":"basic","verify_calls":true,"verify_state":true,"parallel":true,"timeout_ms":60000},"summary":{"total_queries":0,"sat":0,"unsat":0,"unknown":0,"failed_obligations":0,"inconsistent_bases":0,"proven_guards":0,"violatable_guards":0},"query_kind_counts":{"base":0,"obligation":0,"loop_invariant_step":0,"loop_invariant_post":0,"guard_satisfy":0,"guard_violate":0},"verification":{"success":true,"errors":0,"diagnostics":0},"errors":[],"diagnostics":[],"queries":[]}